{
  "name": "@paulmillr/micro-eth-signer",
  "version": "0.17.3",
  "exports": {
    ".": "./src/index.ts",
    "./net.js": "./src/net.ts",
    "./utils.js": "./src/utils.ts",
    "./advanced/abi.js": "./src/advanced/abi.ts",
    "./advanced/kzg.js": "./src/advanced/kzg.ts",
    "./advanced/ssz.js": "./src/advanced/ssz.ts",
    "./advanced/verkle.js": "./src/advanced/verkle.ts"
  },
  "imports": {
    "@noble/curves": "jsr:@noble/curves@^2.0.0",
    "@noble/hashes": "jsr:@noble/hashes@^2.0.0",
    "micro-packed": "jsr:@paulmillr/micro-packed@^0.8.0"
  },
  "publish": {
    "include": [
      "src",
      "jsr.json",
      "LICENSE",
      "README.md"
    ]
  },
  "license": "MIT"
}
